cifi/_core.cpython-312-x86_64-linux-gnu.so
cifi/cli.py
cifi/report.py
cifi/__init__.py
cifi/templates/report.html
cifi.libs/libhts-48b809e4.so.1.21
cifi-0.1.0.dist-info/WHEEL
cifi-0.1.0.dist-info/entry_points.txt
cifi-0.1.0.dist-info/METADATA
cifi-0.1.0.dist-info/RECORD
cifi-0.1.0.dist-info/licenses/LICENSE
