Metadata-Version: 2.2
Name: cifi
Version: 0.1.0
Summary: CiFi - toolkit for downstream processing of CiFi long reads.
Keywords: bioinformatics,chromatin,chromosome-conformation-capture,cifi,hi-c,restriction-enzyme,paired-end,long-reads,pacbio,hifi
Author-Email: Dennis Lab <mhussien@ucdavis.edu>
Maintainer-Email: Mohamed Abuelanin <mhussien@ucdavis.edu>
License: MIT
Classifier: Development Status :: 4 - Beta
Classifier: Environment :: Console
Classifier: Intended Audience :: Science/Research
Classifier: License :: OSI Approved :: MIT License
Classifier: Operating System :: POSIX :: Linux
Classifier: Operating System :: MacOS
Classifier: Programming Language :: Python :: 3
Classifier: Programming Language :: Python :: 3.9
Classifier: Programming Language :: Python :: 3.10
Classifier: Programming Language :: Python :: 3.11
Classifier: Programming Language :: Python :: 3.12
Classifier: Programming Language :: C++
Classifier: Topic :: Scientific/Engineering :: Bio-Informatics
Project-URL: Homepage, https://github.com/mr-eyes/cifi-toolkit
Project-URL: Documentation, https://github.com/mr-eyes/cifi-toolkit#readme
Project-URL: Repository, https://github.com/mr-eyes/cifi-toolkit
Project-URL: Issues, https://github.com/mr-eyes/cifi-toolkit/issues
Project-URL: Changelog, https://github.com/mr-eyes/cifi-toolkit/releases
Requires-Python: >=3.9
Requires-Dist: click>=8.0
Requires-Dist: jinja2>=3.0
Provides-Extra: dev
Requires-Dist: pytest>=7.0; extra == "dev"
Requires-Dist: pytest-cov>=4.0; extra == "dev"
Requires-Dist: ruff>=0.1.0; extra == "dev"
Provides-Extra: pdf
Requires-Dist: weasyprint>=60.0; extra == "pdf"
Provides-Extra: plots
Requires-Dist: matplotlib>=3.5; extra == "plots"
Provides-Extra: all
Requires-Dist: weasyprint>=60.0; extra == "all"
Requires-Dist: matplotlib>=3.5; extra == "all"
Requires-Dist: pytest>=7.0; extra == "all"
Requires-Dist: pytest-cov>=4.0; extra == "all"
